licenseheaders.py
licenseheaders-0.8.8.data/data/templates/agpl-v3.tmpl
licenseheaders-0.8.8.data/data/templates/apache-2.tmpl
licenseheaders-0.8.8.data/data/templates/bsd-3.tmpl
licenseheaders-0.8.8.data/data/templates/cecill-B.tmpl
licenseheaders-0.8.8.data/data/templates/cecill-C.tmpl
licenseheaders-0.8.8.data/data/templates/cecill.tmpl
licenseheaders-0.8.8.data/data/templates/gpl-v3.tmpl
licenseheaders-0.8.8.data/data/templates/lgpl-v2.1.tmpl
licenseheaders-0.8.8.data/data/templates/lgpl-v3.tmpl
licenseheaders-0.8.8.dist-info/LICENSE.txt
licenseheaders-0.8.8.dist-info/METADATA
licenseheaders-0.8.8.dist-info/WHEEL
licenseheaders-0.8.8.dist-info/entry_points.txt
licenseheaders-0.8.8.dist-info/top_level.txt
licenseheaders-0.8.8.dist-info/RECORD
