Metadata-Version: 2.1
Name: licenseheaders
Version: 0.8.8
Summary: Add or change license headers for all files in a directory
Home-page: http://github.com/johann-petrak/licenseheaders
Author: Johann Petrak
Author-email: johann.petrak@gmail.com
License: MIT
Platform: UNKNOWN
Classifier: Development Status :: 5 - Production/Stable
Classifier: License :: OSI Approved :: MIT License
Classifier: Environment :: Console
Classifier: Natural Language :: English
Classifier: Programming Language :: Python :: 3
Classifier: Topic :: Software Development
Classifier: Topic :: Software Development :: Code Generators
Classifier: Intended Audience :: Developers
Requires-Python: >=3.5
